[
  {
    "name": "2.0 ton 80% furnace 14 seer",
    "type": "Furnace",
    "tons": "2.0",
    "description": "Includes 2.0 Ton outdoor condenser, Single stage compressor, Non variable speed blower motor, R410A coil, Honeywell T4 thermostat and 10 year warranty on parts and labor.",
    "seer": "14",
    "price": "6000"
  },
  {
    "name": "3.0 ton 80% furnace 14 seer",
    "type": "Furnace",
    "tons": "3.0",
    "description": "Includes 3.0 Ton outdoor condenser, Single stage compressor, Non variable speed blower motor, R410A coil, Honeywell T4 thermostat and 10 year warranty on parts and labor.",
    "seer": "14",
    "price": "7000"
  },
  {
    "name": "4.0 ton 80% furnace 14 seer",
    "type": "Furnace",
    "tons": "4.0",
    "description": "Includes 4.0 Ton outdoor condenser, Single stage compressor, Non variable speed blower motor, R410A coil, Honeywell T4 thermostat and 10 year warranty on parts and labor.",
    "seer": "14",
    "price": "8000"
  },
  {
    "name": "5.0 ton 80% furnace 14 seer",
    "type": "Furnace",
    "tons": "5.0",
    "description": "Includes 5.0 Ton outdoor condenser, Single stage compressor, Non variable speed blower motor, R410A coil, Honeywell T4 thermostat and 10 year warranty on parts and labor.",
    "seer": "14",
    "price": "9000"
  },
  {
    "name": "2.0 ton air handler 14 seer",
    "type": "Air Handler",
    "tons": "2.0",
    "description": "Includes 2.0 Ton heat pump, Single stage compressor, Non variable speed blower motor, R410A coil , Nest thermostat and 10 year warranty on parts and labor.",
    "seer": "14",
    "price": "7500"
  },
  {
    "name": "3.0 ton air handler 14 seer",
    "type": "Air Handler",
    "tons": "3.0",
    "description": "Includes 3.0 Ton heat pump, Single stage compressor, Non variable speed blower motor, R410A coil, Nest thermostat and 10 year warranty on parts and labor.",
    "seer": "14",
    "price": "8500"
  },
  {
    "name": "4.0 ton air handler 14 seer",
    "type": "Air Handler",
    "tons": "4.0",
    "description": "Includes 4.0 Ton heat pump, Single stage compressor, Non variable speed blower motor, R410A coil, Nest thermostat and 10 year warranty on parts and labor.",
    "seer": "14",
    "price": "9500"
  },
  {
    "name": "5.0 ton air handler 14 seer",
    "type": "Air Handler",
    "tons": "5.0",
    "description": "Includes 5.0 Ton heat pump, Single stage compressor, Non variable speed blower motor, R410A coil, Nest thermostat and 10 year warranty on parts and labor.",
    "seer": "14",
    "price": "10500"
  },
  {
    "name": "2.0 ton 80% furnace 16 seer",
    "type": "Furnace",
    "tons": "2.0",
    "description": "Includes 2.0 Ton outdoor condenser, Single stage compressor, Non variable speed blower motor, R410A coil, Honeywell T4 thermostat and 10 year warranty on parts and labor.",
    "seer": "16",
    "price": "6750"
  },
  {
    "name": "3.0 ton 80% furnace 16 seer",
    "type": "Furnace",
    "tons": "3.0",
    "description": "Includes 3.0 Ton outdoor condenser, Single stage compressor, Non variable speed blower motor, R410A coil, Honeywell T4 thermostat and 10 year warranty on parts and labor.",
    "seer": "16",
    "price": "7560"
  },
  {
    "name": "4.0 ton 80% furnace 16 seer",
    "type": "Furnace",
    "tons": "4.0",
    "description": "Includes 4.0 Ton outdoor condenser, Single stage compressor, Non variable speed blower motor, R410A coil, Honeywell T4 thermostat and 10 year warranty on parts and labor.",
    "seer": "16",
    "price": "8750"
  },
  {
    "name": "5.0 ton 80% furnace 16 seer",
    "type": "Furnace",
    "tons": "5.0",
    "description": "Includes 5.0 Ton outdoor condenser, Single stage compressor, Non variable speed blower motor, R410A coil, Honeywell T4 thermostat and 10 year warranty on parts and labor.",
    "seer": "16",
    "price": "9000"
  },
  {
    "name": "2.0 ton air handler 16 seer",
    "type": "Air Handler",
    "tons": "2.0",
    "description": "Includes 2.0 Ton heat pump, Single stage compressor, Non variable speed blower motor, R410A coil , Nest thermostat and 10 year warranty on parts and labor.",
    "seer": "16",
    "price": "8250"
  },
  {
    "name": "3.0 ton air handler 16 seer",
    "type": "Air Handler",
    "tons": "3.0",
    "description": "Includes 3.0 Ton heat pump, Single stage compressor, Non variable speed blower motor, R410A coil, Nest thermostat and 10 year warranty on parts and labor.",
    "seer": "16",
    "price": "8750"
  },
  {
    "name": "4.0 ton air handler 16 seer",
    "type": "Air Handler",
    "tons": "4.0",
    "description": "Includes 4.0 Ton heat pump, Single stage compressor, Non variable speed blower motor, R410A coil, Nest thermostat and 10 year warranty on parts and labor.",
    "seer": "16",
    "price": "9750"
  },
  {
    "name": "5.0 ton air handler 16 seer",
    "type": "Air Handler",
    "tons": "5.0",
    "description": "Includes 5.0 Ton heat pump, Single stage compressor, Non variable speed blower motor, R410A coil, Nest thermostat and 10 year warranty on parts and labor.",
    "seer": "16",
    "price": "10750"
  }
]